bacx/messages/__init__.py
bacx/messages/constants.py
bacx/messages/publisher.py
bacx/messages/subscriber.py
bacx/storage/__init__.py
bacx/storage/manager.py
bacx/storage/schema.yaml
bacx/storage/engines/__init__.py
bacx/storage/engines/aws_drive.py
bacx/storage/engines/cloud_engine.py
bacx/storage/engines/engine.py
bacx/storage/engines/gcloud_drive.py
bacx/storage/engines/local_drive.py
bacx/utils/__init__.py
bacx/utils/cache_manager.py
bacx/utils/config.py
bacx/utils/debug_utils.py
bacx/utils/dict_utils.py
bacx/utils/import_utils.py
bacx/utils/namedict.py
bacx/utils/profile_utils.py
bacx/worker/__init__.py
bacx/worker/base_fast_worker.py
bacx/worker/base_slow_worker.py
bacx/worker/base_worker.py
bacx/worker/types.py
bacx/worker/pipelines/__init__.py
bacx/worker/pipelines/standard_worker.py
bacx-0.1.8.data/data/bacx/storage/schema.yaml
bacx-0.1.8.data/data/docs/doc_bacx.md
bacx-0.1.8.data/data/docs/doc_messages.md
bacx-0.1.8.data/data/docs/doc_storage.md
bacx-0.1.8.data/data/docs/doc_utils.md
bacx-0.1.8.data/data/docs/doc_worker.md
bacx-0.1.8.dist-info/LICENSE
bacx-0.1.8.dist-info/METADATA
bacx-0.1.8.dist-info/WHEEL
bacx-0.1.8.dist-info/top_level.txt
bacx-0.1.8.dist-info/RECORD
