Metadata-Version: 2.1
Name: bacx
Version: 0.1.8
Summary: CogneXa toolkit.
Home-page: https://github.com/Cognexa/bacx
Author: Cognexa Solutions s.r.o.
Author-email: info@cognexa.com
License: MIT license
Platform: UNKNOWN
Classifier: License :: OSI Approved :: MIT License
Classifier: Programming Language :: Python :: 3.9
Classifier: Operating System :: OS Independent
License-File: LICENSE
Requires-Dist: boto3
Requires-Dist: google-cloud-pubsub
Requires-Dist: google-cloud-storage
Requires-Dist: pyyaml
Requires-Dist: redis
Requires-Dist: requests
Requires-Dist: yamale
